brain_games/__init__.py
brain_games/cli.py
brain_games/games/__init__.py
brain_games/games/brain_calc.py
brain_games/games/brain_even.py
brain_games/games/engine.py
brain_games/scripts/__init__.py
brain_games/scripts/brain_calc.py
brain_games/scripts/brain_even.py
brain_games/scripts/brain_games.py
hexlet_code1-6.1.dist-info/entry_points.txt
hexlet_code1-6.1.dist-info/WHEEL
hexlet_code1-6.1.dist-info/METADATA
hexlet_code1-6.1.dist-info/RECORD
